Metadata-Version: 2.1
Name: tik-afriton
Version: 1.1
Summary: your description
Author: AFRITON
Classifier: Programming Language :: Python :: 3
Classifier: Operating System :: OS Independent
Classifier: License :: OSI Approved :: MIT License
License-File: LICENSE.txt
